whetstone/__init__.py
whetstone-0.6.0.dist-info/WHEEL
whetstone-0.6.0.dist-info/METADATA
whetstone-0.6.0.dist-info/licenses/LICENSE
whetstone-0.6.0.dist-info/RECORD
