Metadata-Version: 2.1
Name: whetstone
Version: 0.6.0
License: MIT
Author-email: Charlie Bini <5003326+cbini@users.noreply.github.com>
Requires-Python: >=3.7
Requires-Dist: oauthlib>=3.1.1
Requires-Dist: requests-oauthlib>=1.3.0
Requires-Dist: requests>=2.27.1
